napari_sketchpose/Custom_cellpose_omni.py
napari_sketchpose/TrainingDialog.py
napari_sketchpose/__init__.py
napari_sketchpose/__main__.py
napari_sketchpose/_reader.py
napari_sketchpose/_sample_data.py
napari_sketchpose/_widget.py
napari_sketchpose/_writer.py
napari_sketchpose/custom_transforms.py
napari_sketchpose/debug.py
napari_sketchpose/io.py
napari_sketchpose/napari.yaml
napari_sketchpose/_tests/__init__.py
napari_sketchpose/_tests/test_reader.py
napari_sketchpose/_tests/test_sample_data.py
napari_sketchpose/_tests/test_widget.py
napari_sketchpose/_tests/test_writer.py
napari_sketchpose/evaluation_training/Custom_cellpose_omni_for_training.py
napari_sketchpose/evaluation_training/evaluate_accuracy.py
napari_sketchpose/evaluation_training/plot_accuracy.py
napari_sketchpose/evaluation_training/run_multiple_trainings.py
napari_sketchpose/evaluation_training/run_multiple_trainings_with_test.py
napari_sketchpose-0.1.8.dist-info/LICENSE
napari_sketchpose-0.1.8.dist-info/METADATA
napari_sketchpose-0.1.8.dist-info/WHEEL
napari_sketchpose-0.1.8.dist-info/entry_points.txt
napari_sketchpose-0.1.8.dist-info/top_level.txt
napari_sketchpose-0.1.8.dist-info/RECORD
