Metadata-Version: 2.1
Name: napari-sketchpose
Version: 0.1.8
Summary: A segmentation plugin to adapt Omnipose implementation to partial labelling.
Author: Clément Cazorla
Author-email: clement.cazorla31@gmail.com
License: GPL-3.0-only
Project-URL: Bug Tracker, https://bitbucket.org/koopa31/napari-sketchpose/issues?status=new&status=open&status=submitted&is_spam=!spam
Project-URL: Documentation, https://sketchpose-doc.readthedocs.io/en/latest/
Project-URL: Source Code, https://bitbucket.org/koopa31/napari-sketchpose/src/master
Project-URL: User Support, https://bitbucket.org/koopa31/napari-sketchpose/issues?status=new&status=open&status=submitted&is_spam=!spam
Classifier: Development Status :: 2 - Pre-Alpha
Classifier: Framework :: napari
Classifier: Intended Audience :: Developers
Classifier: License :: OSI Approved :: GNU General Public License v3 (GPLv3)
Classifier: Operating System :: OS Independent
Classifier: Programming Language :: Python
Classifier: Programming Language :: Python :: 3
Classifier: Programming Language :: Python :: 3 :: Only
Classifier: Programming Language :: Python :: 3.8
Classifier: Programming Language :: Python :: 3.9
Classifier: Programming Language :: Python :: 3.10
Classifier: Topic :: Scientific/Engineering :: Image Processing
Requires-Python: >=3.8
License-File: LICENSE
Requires-Dist: numpy
Requires-Dist: magicgui
Requires-Dist: qtpy
Requires-Dist: cellpose-omni ==0.9.1
Requires-Dist: omnipose ==0.4.4
Requires-Dist: pyqtgraph ==0.13.3
Requires-Dist: matplotlib
Requires-Dist: light-the-torch
Provides-Extra: testing
Requires-Dist: tox ; extra == 'testing'
Requires-Dist: pytest ; extra == 'testing'
Requires-Dist: pytest-cov ; extra == 'testing'
Requires-Dist: pytest-qt ; extra == 'testing'
Requires-Dist: napari ; extra == 'testing'
Requires-Dist: pyqt5 ; extra == 'testing'
